{
  "speaker_andrew": {
    "id": "speaker_andrew",
    "name": "Speaker Andrew",
    "class": "Conference Speaker",
    "dialogBefore": "The Ruby community isn't something you join, it's something you help create!",
    "dialogAfter": "That's what the community is about. Keep contributing!",
    "party": [
      {
        "bugId": "external_dependency",
        "level": 16
      },
      {
        "bugId": "test_pollution",
        "level": 17
      }
    ],
    "prizeMoney": 400,
    "lineOfSight": 4
  },
  "speaker_avi": {
    "id": "speaker_avi",
    "name": "Speaker Avi",
    "class": "Conference Speaker",
    "dialogBefore": "Let go with AI. You won't even need to read the code.",
    "dialogAfter": "When it doesn't work, compound the lesson back in.",
    "party": [
      {
        "bugId": "context_overflow",
        "level": 22
      },
      {
        "bugId": "sql_injection",
        "level": 23
      },
      {
        "bugId": "race_condition",
        "level": 24
      }
    ],
    "prizeMoney": 560,
    "lineOfSight": 4
  },
  "speaker_kieran": {
    "id": "speaker_kieran",
    "name": "Speaker Kieran",
    "class": "Conference Speaker",
    "dialogBefore": "Every bug is data. Fix it once, prevent it forever.",
    "dialogAfter": "Lesson logged. Your system just got smarter.",
    "party": [
      {
        "bugId": "pending_migration",
        "level": 24
      },
      {
        "bugId": "xss_attack",
        "level": 23
      },
      {
        "bugId": "circular_dependency",
        "level": 25
      }
    ],
    "prizeMoney": 600,
    "lineOfSight": 5
  },
  "speaker_matheus": {
    "id": "speaker_matheus",
    "name": "Speaker Matheus",
    "class": "Conference Speaker",
    "dialogBefore": "You don't need engines or new languages. Ruby is all you need.",
    "dialogAfter": "Ten years in and Ruby still brings me joy.",
    "party": [
      {
        "bugId": "no_method_error",
        "level": 6
      },
      {
        "bugId": "flaky_test",
        "level": 6
      }
    ],
    "prizeMoney": 300,
    "lineOfSight": 3
  },
  "test_minion_05": {
    "id": "test_minion_05",
    "name": "Attendee Avery",
    "class": "Conference Attendee",
    "dialogBefore": "I just found my first bug! Want to see it?",
    "dialogAfter": "Ok that bug didn't stand a chance...",
    "party": [
      {
        "bugId": "flaky_test",
        "level": 4
      }
    ],
    "prizeMoney": 100,
    "lineOfSight": 3
  },
  "test_minion_02": {
    "id": "test_minion_02",
    "name": "Attendee Quinn",
    "class": "Conference Attendee",
    "dialogBefore": "I found some bugs in my code! Let me throw them at you!",
    "dialogAfter": "I guess you squashed them...",
    "party": [
      {
        "bugId": "flaky_test",
        "level": 5
      },
      {
        "bugId": "no_method_error",
        "level": 6
      }
    ],
    "prizeMoney": 180,
    "lineOfSight": 3
  },
  "test_minion_03": {
    "id": "test_minion_03",
    "name": "QA Advocate Lee",
    "class": "Testing Fanatic",
    "dialogBefore": "No code ships without fixing these bugs first. Not on my watch!",
    "dialogAfter": "Your gems handled those bugs impressively...",
    "party": [
      {
        "bugId": "external_dependency",
        "level": 8
      },
      {
        "bugId": "brittle_spec",
        "level": 7
      }
    ],
    "prizeMoney": 250,
    "lineOfSight": 4
  },
  "ifat_ribon": {
    "id": "ifat_ribon",
    "name": "Speaker Ifat",
    "class": "Conference Speaker",
    "dialogBefore": "AI can write tests in seconds, but it can't tell you which ones matter (yet).",
    "dialogAfter": "I think you have a good understanding of clear, maintainable tests.",
    "party": [
      {
        "bugId": "flaky_test",
        "level": 9
      },
      {
        "bugId": "external_dependency",
        "level": 8
      },
      {
        "bugId": "slow_test_suite",
        "level": 10
      }
    ],
    "prizeMoney": 350,
    "lineOfSight": 4
  },
  "parking_01": {
    "id": "parking_01",
    "name": "Junior Dev Casey",
    "class": "Junior Developer",
    "dialogBefore": "I just deployed my first app and everything is breaking!",
    "dialogAfter": "Maybe I should have written tests first...",
    "party": [
      {
        "bugId": "no_method_error",
        "level": 11
      },
      {
        "bugId": "centered_div",
        "level": 12
      }
    ],
    "lineOfSight": 3
  },
  "parking_03": {
    "id": "parking_03",
    "name": "Senior Dev Dana",
    "class": "Senior Developer",
    "dialogBefore": "I've been debugging production issues all day. Want to see what I found?",
    "dialogAfter": "You handled those like a pro...",
    "party": [
      {
        "bugId": "race_condition",
        "level": 17
      },
      {
        "bugId": "cors_error",
        "level": 18
      }
    ],
    "lineOfSight": 4
  },
  "avo_adrian": {
    "id": "avo_adrian",
    "name": "Friendly Dev Adrian",
    "class": "Indie Dev",
    "dialogBefore": "Don't worry, I'll be friendly.",
    "dialogAfter": "That was a rush, thanks.",
    "party": [
      {
        "bugId": "memory_leak",
        "level": 17
      },
      {
        "bugId": "missing_assets",
        "level": 19
      }
    ],
    "lineOfSight": 3
  },
  "indie_jeremy": {
    "id": "indie_jeremy",
    "name": "Indie Dev Jeremy",
    "class": "Indie Dev",
    "dialogBefore": "I have my own conference you know, Blue Ridge Ruby.",
    "dialogAfter": "You handled those bugs well. Maybe you should be a speaker!",
    "party": [
      {
        "bugId": "race_condition",
        "level": 14
      },
      {
        "bugId": "csrf_vuln",
        "level": 15
      }
    ],
    "lineOfSight": 3
  },
  "justin_bowen": {
    "id": "justin_bowen",
    "name": "Active Agent Justin",
    "class": "Active Agent",
    "dialogBefore": "An agent is just a controller with a persona. Nothing mystical.",
    "dialogAfter": "Retry logic keeps hallucinations out of production.",
    "party": [
      {
        "bugId": "hallucination",
        "level": 23
      },
      {
        "bugId": "context_overflow",
        "level": 25
      }
    ],
    "prizeMoney": 500,
    "lineOfSight": 3
  }
}